django_antimat
