Metadata-Version: 1.0
Name: django-antimat
Version: 1.0.1
Summary: Django antimat is application for filtering swear words.
Home-page: https://github.com/ruscoder/django_antimat
Author: Vadim
Author-email: Vadim <rusmiligamer@gmail.com>
License: BSD
Keywords: django antimat anti snub antiswear swear words
Platform: UNKNOWN
